{
    "os": "Linux-6.8.9-100.fc38.x86_64-x86_64-with-glibc2.37",
    "python": "3.11.9",
    "heartbeatAt": "2024-10-03T19:47:12.992907",
    "startedAt": "2024-10-03T19:47:12.327045",
    "docker": null,
    "cuda": null,
    "args": [],
    "state": "running",
    "program": "<python with no main file>",
    "git": {
        "remote": "https://github.com/cijerezg/Bittle-RL.git",
        "commit": "ca8a623b54c2d5361820af9bff392a04e2ff5cc9"
    },
    "email": "cijerezg@unal.edu.co",
    "root": "/home/carlos/Documents/Research/Petoi/Bittle-RL",
    "host": "fedora",
    "username": "carlos",
    "executable": "/home/carlos/.virtualenvs/general_env/bin/python",
    "cpu_count": 8,
    "cpu_count_logical": 16,
    "cpu_freq": {
        "current": 2580.48025,
        "min": 2200.0,
        "max": 3800.0
    },
    "cpu_freq_per_core": [
        {
            "current": 3892.338,
            "min": 2200.0,
            "max": 3800.0
        },
        {
            "current": 2200.0,
            "min": 2200.0,
            "max": 3800.0
        },
        {
            "current": 1946.015,
            "min": 2200.0,
            "max": 3800.0
        },
        {
            "current": 2200.0,
            "min": 2200.0,
            "max": 3800.0
        },
        {
            "current": 1730.608,
            "min": 2200.0,
            "max": 3800.0
        },
        {
            "current": 3800.0,
            "min": 2200.0,
            "max": 3800.0
        },
        {
            "current": 2200.0,
            "min": 2200.0,
            "max": 3800.0
        },
        {
            "current": 2200.0,
            "min": 2200.0,
            "max": 3800.0
        },
        {
            "current": 3800.0,
            "min": 2200.0,
            "max": 3800.0
        },
        {
            "current": 2594.869,
            "min": 2200.0,
            "max": 3800.0
        },
        {
            "current": 1731.403,
            "min": 2200.0,
            "max": 3800.0
        },
        {
            "current": 3126.798,
            "min": 2200.0,
            "max": 3800.0
        },
        {
            "current": 1731.502,
            "min": 2200.0,
            "max": 3800.0
        },
        {
            "current": 3892.297,
            "min": 2200.0,
            "max": 3800.0
        },
        {
            "current": 1731.782,
            "min": 2200.0,
            "max": 3800.0
        },
        {
            "current": 2200.0,
            "min": 2200.0,
            "max": 3800.0
        }
    ],
    "disk": {
        "total": 2804.7138671875,
        "used": 302.5699348449707
    },
    "gpu": "NVIDIA GeForce GTX 1080",
    "gpu_count": 1,
    "gpu_devices": [
        {
            "name": "NVIDIA GeForce GTX 1080",
            "memory_total": 8589934592
        }
    ],
    "memory": {
        "total": 31.177444458007812
    }
}
